ewok/__about__.py
ewok/__init__.py
ewok/cli.py
ewok/core.py
ewok/monkey.py
ewok/py.typed
ewok/local_tasks/__init__.py
ewok-0.4.5.dist-info/METADATA
ewok-0.4.5.dist-info/WHEEL
ewok-0.4.5.dist-info/licenses/LICENSE.txt
ewok-0.4.5.dist-info/RECORD
