Metadata-Version: 2.4
Name: ewok
Version: 0.4.5
Summary: Education Warehouse Octopus Kit - Extensible CLI framework with plugin support
Project-URL: Documentation, https://github.com/educationwarehouse/ewok#readme
Project-URL: Issues, https://github.com/educationwarehouse/ewok/issues
Project-URL: Source, https://github.com/educationwarehouse/ewok
Author-email: Robin van der Noord <robin.vdn@educationwarehouse.nl>, Remco Boerma <remco.b@educationwarehouse.nl>
License-File: LICENSE.txt
Requires-Python: >=3.12
Requires-Dist: docstring-parser<1
Requires-Dist: fabric<4,>=3.1
Requires-Dist: invoke<3,>=2.1
Requires-Dist: termcolor<3
Requires-Dist: typing-extensions<5
